LICENSE
MANIFEST.in
README.rst
setup.py
gax_google_logging_v2.egg-info/PKG-INFO
gax_google_logging_v2.egg-info/SOURCES.txt
gax_google_logging_v2.egg-info/dependency_links.txt
gax_google_logging_v2.egg-info/namespace_packages.txt
gax_google_logging_v2.egg-info/requires.txt
gax_google_logging_v2.egg-info/top_level.txt
google/__init__.py
google/__init__.pyc
google/cloud/__init__.py
google/cloud/__init__.pyc
google/cloud/logging/__init__.py
google/cloud/logging/__init__.pyc
google/cloud/logging/v2/__init__.py
google/cloud/logging/v2/config_service_v2_api.py
google/cloud/logging/v2/config_service_v2_client_config.json
google/cloud/logging/v2/logging_service_v2_api.py
google/cloud/logging/v2/logging_service_v2_client_config.json
google/cloud/logging/v2/metrics_service_v2_api.py
google/cloud/logging/v2/metrics_service_v2_client_config.json